{
"schedule_effective_date": "2025-10-11",
  "routes": 
    {
      "trains": [
        {
          "train_number": "S1001",
          "type": "直达车",
          "stops": [
            { "station": "上海南", "arrival": "--", "departure": "5:20" },
            { "station": "金山卫", "arrival": "5:54", "departure": "--" }
          ]
        },
        {
          "train_number": "S1201",
          "type": "站站停",
          "stops": [
            { "station": "上海南", "arrival": "--", "departure": "5:50" },
            { "station": "春申", "arrival": "6:00", "departure": "6:01" },
            { "station": "新桥", "arrival": "6:09", "departure": "6:10" },
            { "station": "车墩", "arrival": "6:17", "departure": "6:18" },
            { "station": "叶榭", "arrival": "6:25", "departure": "6:26" },
            { "station": "亭林", "arrival": "6:32", "departure": "6:33" },
            { "station": "金山园区", "arrival": "6:39", "departure": "6:40" },
            { "station": "金山卫", "arrival": "6:50", "departure": "--" }
          ]
        },
        {
          "train_number": "S1101",
          "type": "大站车",
          "stops": [
            { "station": "上海南", "arrival": "--", "departure": "6:18" },
            { "station": "新桥", "arrival": "6:33", "departure": "6:34" },
            { "station": "亭林", "arrival": "6:47", "departure": "6:48" },
            { "station": "金山卫", "arrival": "7:01", "departure": "--" }
          ]
        },
        {
          "train_number": "S1003",
          "type": "直达车",
          "stops": [
            { "station": "上海南", "arrival": "--", "departure": "6:45" },
            { "station": "金山卫", "arrival": "7:21", "departure": "--" }
          ]
        },
        {
          "train_number": "S1005",
          "type": "直达车",
          "stops": [
            { "station": "上海南", "arrival": "--", "departure": "7:15" },
            { "station": "金山卫", "arrival": "7:49", "departure": "--" }
          ]
        },
        {
          "train_number": "S1007",
          "type": "直达车",
          "stops": [
            { "station": "上海南", "arrival": "--", "departure": "7:40" },
            { "station": "金山卫", "arrival": "8:14", "departure": "--" }
          ]
        },
        {
          "train_number": "S1601",
          "type": "站站停",
          "stops": [
            { "station": "莘庄", "arrival": "--", "departure": "7:55" },
            { "station": "春申", "arrival": "8:01", "departure": "8:02" },
            { "station": "新桥", "arrival": "8:10", "departure": "8:11" },
            { "station": "车墩", "arrival": "8:18", "departure": "8:26" },
            { "station": "叶榭", "arrival": "8:33", "departure": "8:34" },
            { "station": "亭林", "arrival": "8:40", "departure": "8:41" },
            { "station": "金山园区", "arrival": "8:47", "departure": "8:48" },
            { "station": "金山卫", "arrival": "8:58", "departure": "--" }
          ]
        },
        {
          "train_number": "S1009",
          "type": "直达车",
          "stops": [
            { "station": "上海南", "arrival": "--", "departure": "8:03" },
            { "station": "金山卫", "arrival": "8:39", "departure": "--" }
          ]
        },
        {
          "train_number": "S1209",
          "type": "站站停",
          "stops": [
            { "station": "上海南", "arrival": "--", "departure": "8:23" },
            { "station": "春申", "arrival": "8:35", "departure": "8:36" },
            { "station": "新桥", "arrival": "8:45", "departure": "8:45" },
            { "station": "车墩", "arrival": "8:52", "departure": "8:53" },
            { "station": "叶榭", "arrival": "9:00", "departure": "9:01" },
            { "station": "亭林", "arrival": "9:07", "departure": "9:08" },
            { "station": "金山园区", "arrival": "9:14", "departure": "9:15" },
            { "station": "金山卫", "arrival": "9:25", "departure": "--" }
          ]
        },
        {
          "train_number": "S1203",
          "type": "站站停",
          "stops": [
            { "station": "上海南", "arrival": "--", "departure": "8:50" },
            { "station": "春申", "arrival": "9:00", "departure": "9:01" },
            { "station": "新桥", "arrival": "9:09", "departure": "9:10" },
            { "station": "车墩", "arrival": "9:17", "departure": "9:18" },
            { "station": "叶榭", "arrival": "9:25", "departure": "9:26" },
            { "station": "亭林", "arrival": "9:32", "departure": "9:33" },
            { "station": "金山园区", "arrival": "9:39", "departure": "9:40" },
            { "station": "金山卫", "arrival": "9:50", "departure": "--" }
          ]
        },
        {
          "train_number": "S1605",
          "type": "大站车",
          "stops": [
            { "station": "春申", "arrival": "--", "departure": "9:32" },
            { "station": "新桥", "arrival": "9:38", "departure": "9:39" },
            { "station": "车墩", "arrival": "9:47", "departure": "9:48" },
            { "station": "叶榭", "arrival": "9:55", "departure": "9:56" },
            { "station": "亭林", "arrival": "10:03", "departure": "10:04" },
            { "station": "金山园区", "arrival": "10:10", "departure": "10:11" },
            { "station": "金山卫", "arrival": "10:28", "departure": "--" }
          ]
        },
        {
          "train_number": "S1607",
          "type": "大站车",
          "stops": [
            { "station": "春申", "arrival": "--", "departure": "9:49" },
            { "station": "新桥", "arrival": "9:56", "departure": "9:57" },
            { "station": "车墩", "arrival": "10:05", "departure": "10:06" },
            { "station": "叶榭", "arrival": "10:13", "departure": "10:14" },
            { "station": "亭林", "arrival": "10:21", "departure": "10:22" },
            { "station": "金山园区", "arrival": "10:28", "departure": "10:29" },
            { "station": "金山卫", "arrival": "10:46", "departure": "--" }
          ]
        },
        {
          "train_number": "S1151",
          "type": "大站车",
          "stops": [
            { "station": "上海南", "arrival": "--", "departure": "10:21" },
            { "station": "车墩", "arrival": "10:40", "departure": "10:41" },
            { "station": "亭林", "arrival": "10:50", "departure": "10:51" },
            { "station": "金山卫", "arrival": "11:04", "departure": "--" }
          ]
        },
        {
          "train_number": "S1609",
          "type": "站站停",
          "stops": [
            { "station": "莘庄", "arrival": "--", "departure": "10:41" },
            { "station": "春申", "arrival": "10:47", "departure": "10:48" },
            { "station": "新桥", "arrival": "10:56", "departure": "10:57" },
            { "station": "车墩", "arrival": "11:04", "departure": "11:05" },
            { "station": "叶榭", "arrival": "11:12", "departure": "11:13" },
            { "station": "亭林", "arrival": "11:19", "departure": "11:20" },
            { "station": "金山园区", "arrival": "11:26", "departure": "11:27" },
            { "station": "金山卫", "arrival": "11:37", "departure": "--" }
          ]
        },
        {
          "train_number": "S1635",
          "type": "站站停",
          "stops": [
            { "station": "莘庄", "arrival": "--", "departure": "11:25" },
            { "station": "春申", "arrival": "11:31", "departure": "11:32" },
            { "station": "新桥", "arrival": "11:40", "departure": "11:41" },
            { "station": "车墩", "arrival": "11:48", "departure": "11:49" },
            { "station": "叶榭", "arrival": "11:56", "departure": "11:57" },
            { "station": "亭林", "arrival": "12:03", "departure": "12:04" },
            { "station": "金山园区", "arrival": "12:10", "departure": "12:11" },
            { "station": "金山卫", "arrival": "12:21", "departure": "--" }
          ]
        },
        {
          "train_number": "S1611",
          "type": "站站停",
          "stops": [
            { "station": "莘庄", "arrival": "--", "departure": "12:05" },
            { "station": "春申", "arrival": "12:11", "departure": "12:12" },
            { "station": "新桥", "arrival": "12:20", "departure": "12:21" },
            { "station": "车墩", "arrival": "12:28", "departure": "12:29" },
            { "station": "叶榭", "arrival": "12:36", "departure": "12:37" },
            { "station": "亭林", "arrival": "12:43", "departure": "12:44" },
            { "station": "金山园区", "arrival": "12:50", "departure": "12:51" },
            { "station": "金山卫", "arrival": "13:01", "departure": "--" }
          ]
        },
        {
          "train_number": "S1153",
          "type": "大站车",
          "stops": [
            { "station": "上海南", "arrival": "--", "departure": "12:25" },
            { "station": "车墩", "arrival": "12:44", "departure": "12:45" },
            { "station": "亭林", "arrival": "12:54", "departure": "12:55" },
            { "station": "金山卫", "arrival": "13:08", "departure": "--" }
          ]
        },
        {
          "train_number": "S1613",
          "type": "站站停",
          "stops": [
            { "station": "莘庄", "arrival": "--", "departure": "12:53" },
            { "station": "春申", "arrival": "12:59", "departure": "13:00" },
            { "station": "新桥", "arrival": "13:08", "departure": "13:09" },
            { "station": "车墩", "arrival": "13:16", "departure": "13:17" },
            { "station": "叶榭", "arrival": "13:24", "departure": "13:25" },
            { "station": "亭林", "arrival": "13:31", "departure": "13:32" },
            { "station": "金山园区", "arrival": "13:38", "departure": "13:39" },
            { "station": "金山卫", "arrival": "13:49", "departure": "--" }
          ]
        },
        {
          "train_number": "S1643",
          "type": "大站车",
          "stops": [
            { "station": "莘庄", "arrival": "--", "departure": "13:40" },
            { "station": "新桥", "arrival": "13:51", "departure": "13:52" },
            { "station": "亭林", "arrival": "14:05", "departure": "14:06" },
            { "station": "金山卫", "arrival": "14:19", "departure": "--" }
          ]
        },
        {
          "train_number": "S1615",
          "type": "站站停",
          "stops": [
            { "station": "莘庄", "arrival": "--", "departure": "14:05" },
            { "station": "春申", "arrival": "14:11", "departure": "14:12" },
            { "station": "新桥", "arrival": "14:20", "departure": "14:21" },
            { "station": "车墩", "arrival": "14:28", "departure": "14:29" },
            { "station": "叶榭", "arrival": "14:36", "departure": "14:37" },
            { "station": "亭林", "arrival": "14:43", "departure": "14:44" },
            { "station": "金山园区", "arrival": "14:50", "departure": "14:51" },
            { "station": "金山卫", "arrival": "15:01", "departure": "--" }
          ]
        },
        {
          "train_number": "S1155",
          "type": "大站车",
          "stops": [
            { "station": "上海南", "arrival": "--", "departure": "14:39" },
            { "station": "车墩", "arrival": "14:58", "departure": "14:59" },
            { "station": "亭林", "arrival": "15:08", "departure": "15:09" },
            { "station": "金山卫", "arrival": "15:22", "departure": "--" }
          ]
        },
        {
          "train_number": "S1617",
          "type": "站站停",
          "stops": [
            { "station": "莘庄", "arrival": "--", "departure": "15:07" },
            { "station": "春申", "arrival": "15:13", "departure": "15:14" },
            { "station": "新桥", "arrival": "15:22", "departure": "15:23" },
            { "station": "车墩", "arrival": "15:30", "departure": "15:31" },
            { "station": "叶榭", "arrival": "15:38", "departure": "15:39" },
            { "station": "亭林", "arrival": "15:45", "departure": "15:46" },
            { "station": "金山园区", "arrival": "15:52", "departure": "15:53" },
            { "station": "金山卫", "arrival": "16:03", "departure": "--" }
          ]
        },
        {
          "train_number": "S1637",
          "type": "站站停",
          "stops": [
            { "station": "莘庄", "arrival": "--", "departure": "15:35" },
            { "station": "春申", "arrival": "15:42", "departure": "15:43" },
            { "station": "新桥", "arrival": "15:51", "departure": "15:52" },
            { "station": "车墩", "arrival": "15:59", "departure": "16:00" },
            { "station": "叶榭", "arrival": "16:07", "departure": "16:08" },
            { "station": "亭林", "arrival": "16:14", "departure": "16:15" },
            { "station": "金山园区", "arrival": "16:21", "departure": "16:22" },
            { "station": "金山卫", "arrival": "16:32", "departure": "--" }
          ]
        },
        {
          "train_number": "S1619",
          "type": "站站停",
          "stops": [
            { "station": "莘庄", "arrival": "--", "departure": "15:50" },
            { "station": "春申", "arrival": "15:56", "departure": "15:57" },
            { "station": "新桥", "arrival": "16:05", "departure": "16:06" },
            { "station": "车墩", "arrival": "16:13", "departure": "16:14" },
            { "station": "叶榭", "arrival": "16:21", "departure": "16:22" },
            { "station": "亭林", "arrival": "16:28", "departure": "16:29" },
            { "station": "金山园区", "arrival": "16:35", "departure": "16:36" },
            { "station": "金山卫", "arrival": "16:46", "departure": "--" }
          ]
        },
        {
          "train_number": "S1621",
          "type": "站站停",
          "stops": [
            { "station": "莘庄", "arrival": "--", "departure": "16:21" },
            { "station": "春申", "arrival": "16:27", "departure": "16:28" },
            { "station": "新桥", "arrival": "16:36", "departure": "16:37" },
            { "station": "车墩", "arrival": "16:44", "departure": "16:45" },
            { "station": "叶榭", "arrival": "16:52", "departure": "16:53" },
            { "station": "亭林", "arrival": "16:59", "departure": "17:00" },
            { "station": "金山园区", "arrival": "17:06", "departure": "17:07" },
            { "station": "金山卫", "arrival": "17:17", "departure": "--" }
          ]
        },
        {
          "train_number": "S1157",
          "type": "大站车",
          "stops": [
            { "station": "上海南", "arrival": "--", "departure": "17:04" },
            { "station": "车墩", "arrival": "17:23", "departure": "17:24" },
            { "station": "亭林", "arrival": "17:33", "departure": "17:34" },
            { "station": "金山卫", "arrival": "17:47", "departure": "--" }
          ]
        },
        {
          "train_number": "S1623",
          "type": "站站停",
          "stops": [
            { "station": "莘庄", "arrival": "--", "departure": "17:16" },
            { "station": "春申", "arrival": "17:22", "departure": "17:23" },
            { "station": "新桥", "arrival": "17:31", "departure": "17:32" },
            { "station": "车墩", "arrival": "17:39", "departure": "17:40" },
            { "station": "叶榭", "arrival": "17:47", "departure": "17:48" },
            { "station": "亭林", "arrival": "17:54", "departure": "17:55" },
            { "station": "金山园区", "arrival": "18:01", "departure": "18:02" },
            { "station": "金山卫", "arrival": "18:12", "departure": "--" }
          ]
        },
        {
          "train_number": "S1141",
          "type": "大站车",
          "stops": [
            { "station": "上海南", "arrival": "--", "departure": "17:35" },
            { "station": "新桥", "arrival": "17:45", "departure": "17:46" },
            { "station": "车墩", "arrival": "18:02", "departure": "18:03" },
            { "station": "金山卫", "arrival": "18:22", "departure": "--" }
          ]
        },
        {
          "train_number": "S1011",
          "type": "直达车",
          "stops": [
            { "station": "上海南", "arrival": "--", "departure": "18:10" },
            { "station": "金山卫", "arrival": "18:45", "departure": "--" }
          ]
        },
        {
          "train_number": "S1625",
          "type": "站站停",
          "stops": [
            { "station": "莘庄", "arrival": "--", "departure": "18:19" },
            { "station": "春申", "arrival": "18:25", "departure": "18:27" },
            { "station": "新桥", "arrival": "18:35", "departure": "18:37" },
            { "station": "车墩", "arrival": "18:44", "departure": "18:46" },
            { "station": "叶榭", "arrival": "18:53", "departure": "18:55" },
            { "station": "亭林", "arrival": "19:01", "departure": "19:03" },
            { "station": "金山园区", "arrival": "19:09", "departure": "19:11" },
            { "station": "金山卫", "arrival": "19:21", "departure": "--" }
          ]
        },
        {
          "train_number": "S1143",
          "type": "大站车",
          "stops": [
            { "station": "上海南", "arrival": "--", "departure": "18:40" },
            { "station": "新桥", "arrival": "18:50", "departure": "18:52" },
            { "station": "车墩", "arrival": "19:00", "departure": "19:02" },
            { "station": "金山卫", "arrival": "19:30", "departure": "--" }
          ]
        },
        {
          "train_number": "S1013",
          "type": "直达车",
          "stops": [
            { "station": "上海南", "arrival": "--", "departure": "19:06" },
            { "station": "金山卫", "arrival": "19:40", "departure": "--" }
          ]
        },
        {
          "train_number": "S1627",
          "type": "站站停",
          "stops": [
            { "station": "莘庄", "arrival": "--", "departure": "19:20" },
            { "station": "春申", "arrival": "19:26", "departure": "19:28" },
            { "station": "新桥", "arrival": "19:36", "departure": "19:38" },
            { "station": "车墩", "arrival": "19:45", "departure": "19:47" },
            { "station": "叶榭", "arrival": "19:54", "departure": "19:56" },
            { "station": "亭林", "arrival": "20:02", "departure": "20:04" },
            { "station": "金山园区", "arrival": "20:10", "departure": "20:12" },
            { "station": "金山卫", "arrival": "20:22", "departure": "--" }
          ]
        },
        {
          "train_number": "S1205",
          "type": "站站停",
          "stops": [
            { "station": "上海南", "arrival": "--", "departure": "19:35" },
            { "station": "春申", "arrival": "19:45", "departure": "19:47" },
            { "station": "新桥", "arrival": "19:55", "departure": "19:57" },
            { "station": "车墩", "arrival": "20:04", "departure": "20:06" },
            { "station": "叶榭", "arrival": "20:13", "departure": "20:15" },
            { "station": "亭林", "arrival": "20:21", "departure": "20:23" },
            { "station": "金山园区", "arrival": "20:29", "departure": "20:31" },
            { "station": "金山卫", "arrival": "20:41", "departure": "--" }
          ]
        },
        {
          "train_number": "S1629",
          "type": "站站停",
          "stops": [
            { "station": "莘庄", "arrival": "--", "departure": "20:10" },
            { "station": "春申", "arrival": "20:16", "departure": "20:17" },
            { "station": "新桥", "arrival": "20:25", "departure": "20:26" },
            { "station": "车墩", "arrival": "20:33", "departure": "20:34" },
            { "station": "叶榭", "arrival": "20:41", "departure": "20:42" },
            { "station": "亭林", "arrival": "20:48", "departure": "20:49" },
            { "station": "金山园区", "arrival": "20:55", "departure": "20:56" },
            { "station": "金山卫", "arrival": "21:06", "departure": "--" }
          ]
        },
        {
          "train_number": "S1207",
          "type": "站站停",
          "stops": [
            { "station": "上海南", "arrival": "--", "departure": "21:00" },
            { "station": "春申", "arrival": "21:10", "departure": "21:11" },
            { "station": "新桥", "arrival": "21:19", "departure": "21:20" },
            { "station": "车墩", "arrival": "21:27", "departure": "21:28" },
            { "station": "叶榭", "arrival": "21:35", "departure": "21:36" },
            { "station": "亭林", "arrival": "21:42", "departure": "21:43" },
            { "station": "金山园区", "arrival": "21:49", "departure": "21:50" },
            { "station": "金山卫", "arrival": "22:00", "departure": "--" }
          ]
        },
        {
          "train_number": "S1633",
          "type": "站站停",
          "stops": [
            { "station": "莘庄", "arrival": "--", "departure": "21:49" },
            { "station": "春申", "arrival": "21:55", "departure": "21:56" },
            { "station": "新桥", "arrival": "22:04", "departure": "22:05" },
            { "station": "车墩", "arrival": "22:12", "departure": "22:13" },
            { "station": "叶榭", "arrival": "22:20", "departure": "22:21" },
            { "station": "亭林", "arrival": "22:27", "departure": "22:28" },
            { "station": "金山园区", "arrival": "22:34", "departure": "22:35" },
            { "station": "金山卫", "arrival": "22:45", "departure": "--" }
          ]
        },
        {
          "train_number": "S1211",
          "type": "站站停",
          "stops": [
            { "station": "上海南", "arrival": "--", "departure": "21:57" },
            { "station": "春申", "arrival": "22:08", "departure": "22:09" },
            { "station": "新桥", "arrival": "22:17", "departure": "22:18" },
            { "station": "车墩", "arrival": "22:25", "departure": "22:26" },
            { "station": "叶榭", "arrival": "22:33", "departure": "22:34" },
            { "station": "亭林", "arrival": "22:40", "departure": "22:41" },
            { "station": "金山园区", "arrival": "22:47", "departure": "22:48" },
            { "station": "金山卫", "arrival": "22:58", "departure": "--" }
          ]
        },
  
        {
          "train_number": "S1212",
          "type": "站站停",
          "stops": [
            { "station": "金山卫", "arrival": "--", "departure": "6:00" },
            { "station": "金山园区", "arrival": "6:09", "departure": "6:10" },
            { "station": "亭林", "arrival": "6:16", "departure": "6:17" },
            { "station": "叶榭", "arrival": "6:23", "departure": "6:24" },
            { "station": "车墩", "arrival": "6:31", "departure": "6:32" },
            { "station": "新桥", "arrival": "6:39", "departure": "6:40" },
            { "station": "春申", "arrival": "6:48", "departure": "6:49" },
            { "station": "莘庄", "arrival": "6:54", "departure": "6:55" },
            { "station": "上海南", "arrival": "7:02", "departure": "--" }
          ]
        },
        {
          "train_number": "S1604",
          "type": "站站停",
          "stops": [
            { "station": "金山卫", "arrival": "--", "departure": "6:22" },
            { "station": "金山园区", "arrival": "6:31", "departure": "6:32" },
            { "station": "亭林", "arrival": "6:38", "departure": "6:39" },
            { "station": "叶榭", "arrival": "6:45", "departure": "6:46" },
            { "station": "车墩", "arrival": "6:53", "departure": "6:54" },
            { "station": "新桥", "arrival": "7:01", "departure": "7:02" },
            { "station": "春申", "arrival": "7:10", "departure": "7:11" },
            { "station": "莘庄", "arrival": "7:16", "departure": "--" }
          ]
        },
        {
          "train_number": "S1002",
          "type": "直达车",
          "stops": [
            { "station": "金山卫", "arrival": "--", "departure": "6:52" },
            { "station": "上海南", "arrival": "7:26", "departure": "--" }
          ]
        },
        {
          "train_number": "S1004",
          "type": "直达车",
          "stops": [
            { "station": "金山卫", "arrival": "--", "departure": "7:14" },
            { "station": "上海南", "arrival": "7:48", "departure": "--" }
          ]
        },
        {
          "train_number": "S1142",
          "type": "大站车",
          "stops": [
            { "station": "金山卫", "arrival": "--", "departure": "7:20" },
            { "station": "车墩", "arrival": "7:38", "departure": "7:40" },
            { "station": "新桥", "arrival": "7:47", "departure": "7:49" },
            { "station": "上海南", "arrival": "8:10", "departure": "--" }
          ]
        },
        {
          "train_number": "S1152",
          "type": "大站车",
          "stops": [
            { "station": "金山卫", "arrival": "--", "departure": "7:33" },
            { "station": "亭林", "arrival": "7:45", "departure": "7:47" },
            { "station": "车墩", "arrival": "7:56", "departure": "7:58" },
            { "station": "上海南", "arrival": "8:30", "departure": "--" }
          ]
        },
        {
          "train_number": "S1202",
          "type": "站站停",
          "stops": [
            { "station": "金山卫", "arrival": "--", "departure": "7:45" },
            { "station": "金山园区", "arrival": "7:54", "departure": "7:56" },
            { "station": "亭林", "arrival": "8:02", "departure": "8:04" },
            { "station": "叶榭", "arrival": "8:10", "departure": "8:12" },
            { "station": "车墩", "arrival": "8:19", "departure": "8:21" },
            { "station": "新桥", "arrival": "8:28", "departure": "8:30" },
            { "station": "春申", "arrival": "8:38", "departure": "8:40" },
            { "station": "莘庄", "arrival": "8:47", "departure": "8:50" },
            { "station": "上海南", "arrival": "8:57", "departure": "--" }
          ]
        },
        {
          "train_number": "S1606",
          "type": "站站停",
          "stops": [
            { "station": "金山卫", "arrival": "--", "departure": "8:10" },
            { "station": "金山园区", "arrival": "8:19", "departure": "8:21" },
            { "station": "亭林", "arrival": "8:27", "departure": "8:29" },
            { "station": "叶榭", "arrival": "8:35", "departure": "8:37" },
            { "station": "车墩", "arrival": "8:44", "departure": "8:46" },
            { "station": "新桥", "arrival": "8:53", "departure": "8:55" },
            { "station": "春申", "arrival": "9:03", "departure": "9:05" },
            { "station": "莘庄", "arrival": "9:13", "departure": "--" }
          ]
        },
        {
          "train_number": "S1608",
          "type": "站站停",
          "stops": [
            { "station": "金山卫", "arrival": "--", "departure": "8:28" },
            { "station": "金山园区", "arrival": "8:37", "departure": "8:39" },
            { "station": "亭林", "arrival": "8:45", "departure": "8:47" },
            { "station": "叶榭", "arrival": "8:53", "departure": "8:55" },
            { "station": "车墩", "arrival": "9:02", "departure": "9:04" },
            { "station": "新桥", "arrival": "9:11", "departure": "9:13" },
            { "station": "春申", "arrival": "9:21", "departure": "9:23" },
            { "station": "莘庄", "arrival": "9:30", "departure": "--" }
          ]
        },
        {
          "train_number": "S1104",
          "type": "大站车",
          "stops": [
            { "station": "金山卫", "arrival": "--", "departure": "9:03" },
            { "station": "亭林", "arrival": "9:15", "departure": "9:16" },
            { "station": "新桥", "arrival": "9:30", "departure": "9:31" },
            { "station": "上海南", "arrival": "9:47", "departure": "--" }
          ]
        },
        {
          "train_number": "S1610",
          "type": "站站停",
          "stops": [
            { "station": "金山卫", "arrival": "--", "departure": "9:25" },
            { "station": "金山园区", "arrival": "9:34", "departure": "9:35" },
            { "station": "亭林", "arrival": "9:41", "departure": "9:42" },
            { "station": "叶榭", "arrival": "9:48", "departure": "9:49" },
            { "station": "车墩", "arrival": "9:56", "departure": "9:57" },
            { "station": "新桥", "arrival": "10:04", "departure": "10:05" },
            { "station": "春申", "arrival": "10:13", "departure": "10:14" },
            { "station": "莘庄", "arrival": "10:21", "departure": "--" }
          ]
        },
        {
          "train_number": "S1636",
          "type": "站站停",
          "stops": [
            { "station": "金山卫", "arrival": "--", "departure": "10:05" },
            { "station": "金山园区", "arrival": "10:14", "departure": "10:15" },
            { "station": "亭林", "arrival": "10:21", "departure": "10:22" },
            { "station": "叶榭", "arrival": "10:28", "departure": "10:29" },
            { "station": "车墩", "arrival": "10:36", "departure": "10:37" },
            { "station": "新桥", "arrival": "10:44", "departure": "10:45" },
            { "station": "春申", "arrival": "10:53", "departure": "10:54" },
            { "station": "莘庄", "arrival": "11:00", "departure": "--" }
          ]
        },
        {
          "train_number": "S1612",
          "type": "站站停",
          "stops": [
            { "station": "金山卫", "arrival": "--", "departure": "10:35" },
            { "station": "金山园区", "arrival": "10:44", "departure": "10:45" },
            { "station": "亭林", "arrival": "10:51", "departure": "10:52" },
            { "station": "叶榭", "arrival": "10:58", "departure": "10:59" },
            { "station": "车墩", "arrival": "11:06", "departure": "11:07" },
            { "station": "新桥", "arrival": "11:14", "departure": "11:15" },
            { "station": "春申", "arrival": "11:23", "departure": "11:24" },
            { "station": "莘庄", "arrival": "11:32", "departure": "--" }
          ]
        },
        {
          "train_number": "S1106",
          "type": "大站车",
          "stops": [
            { "station": "金山卫", "arrival": "--", "departure": "11:19" },
            { "station": "亭林", "arrival": "11:31", "departure": "11:32" },
            { "station": "新桥", "arrival": "11:45", "departure": "11:46" },
            { "station": "上海南", "arrival": "12:02", "departure": "--" }
          ]
        },
        {
          "train_number": "S1614",
          "type": "站站停",
          "stops": [
            { "station": "金山卫", "arrival": "--", "departure": "11:29" },
            { "station": "金山园区", "arrival": "11:38", "departure": "11:39" },
            { "station": "亭林", "arrival": "11:45", "departure": "11:46" },
            { "station": "叶榭", "arrival": "11:52", "departure": "11:53" },
            { "station": "车墩", "arrival": "12:00", "departure": "12:01" },
            { "station": "新桥", "arrival": "12:08", "departure": "12:09" },
            { "station": "春申", "arrival": "12:17", "departure": "12:18" },
            { "station": "莘庄", "arrival": "12:25", "departure": "--" }
          ]
        },
        {
          "train_number": "S1644",
          "type": "大站车",
          "stops": [
            { "station": "金山卫", "arrival": "--", "departure": "12:30" },
            { "station": "亭林", "arrival": "12:42", "departure": "12:43" },
            { "station": "新桥", "arrival": "12:52", "departure": "12:53" },
            { "station": "莘庄", "arrival": "13:07", "departure": "--" }
          ]
        },
        {
          "train_number": "S1616",
          "type": "站站停",
          "stops": [
            { "station": "金山卫", "arrival": "--", "departure": "12:42" },
            { "station": "金山园区", "arrival": "12:51", "departure": "12:52" },
            { "station": "亭林", "arrival": "12:58", "departure": "12:59" },
            { "station": "叶榭", "arrival": "13:05", "departure": "13:06" },
            { "station": "车墩", "arrival": "13:13", "departure": "13:14" },
            { "station": "新桥", "arrival": "13:21", "departure": "13:22" },
            { "station": "春申", "arrival": "13:30", "departure": "13:31" },
            { "station": "莘庄", "arrival": "13:38", "departure": "--" }
          ]
        },
        {
          "train_number": "S1108",
          "type": "大站车",
          "stops": [
            { "station": "金山卫", "arrival": "--", "departure": "13:26" },
            { "station": "亭林", "arrival": "13:38", "departure": "13:39" },
            { "station": "新桥", "arrival": "13:52", "departure": "13:53" },
            { "station": "上海南", "arrival": "14:09", "departure": "--" }
          ]
        },
        {
          "train_number": "S1618",
          "type": "站站停",
          "stops": [
            { "station": "金山卫", "arrival": "--", "departure": "13:53" },
            { "station": "金山园区", "arrival": "14:02", "departure": "14:03" },
            { "station": "亭林", "arrival": "14:09", "departure": "14:10" },
            { "station": "叶榭", "arrival": "14:16", "departure": "14:17" },
            { "station": "车墩", "arrival": "14:24", "departure": "14:25" },
            { "station": "新桥", "arrival": "14:32", "departure": "14:35" },
            { "station": "春申", "arrival": "14:43", "departure": "14:44" },
            { "station": "莘庄", "arrival": "14:51", "departure": "--" }
          ]
        },
        {
          "train_number": "S1638",
          "type": "站站停",
          "stops": [
            { "station": "金山卫", "arrival": "--", "departure": "14:21" },
            { "station": "金山园区", "arrival": "14:30", "departure": "14:31" },
            { "station": "亭林", "arrival": "14:37", "departure": "14:38" },
            { "station": "叶榭", "arrival": "14:44", "departure": "14:45" },
            { "station": "车墩", "arrival": "14:52", "departure": "14:53" },
            { "station": "新桥", "arrival": "15:00", "departure": "15:01" },
            { "station": "春申", "arrival": "15:10", "departure": "15:11" },
            { "station": "莘庄", "arrival": "15:17", "departure": "--" }
          ]
        },
        {
          "train_number": "S1620",
          "type": "站站停",
          "stops": [
            { "station": "金山卫", "arrival": "--", "departure": "14:33" },
            { "station": "金山园区", "arrival": "14:42", "departure": "14:43" },
            { "station": "亭林", "arrival": "14:49", "departure": "14:50" },
            { "station": "叶榭", "arrival": "14:56", "departure": "14:57" },
            { "station": "车墩", "arrival": "15:04", "departure": "15:05" },
            { "station": "新桥", "arrival": "15:12", "departure": "15:13" },
            { "station": "春申", "arrival": "15:21", "departure": "15:22" },
            { "station": "莘庄", "arrival": "15:29", "departure": "--" }
          ]
        },
        {
          "train_number": "S1622",
          "type": "站站停",
          "stops": [
            { "station": "金山卫", "arrival": "--", "departure": "15:02" },
            { "station": "金山园区", "arrival": "15:11", "departure": "15:12" },
            { "station": "亭林", "arrival": "15:18", "departure": "15:19" },
            { "station": "叶榭", "arrival": "15:25", "departure": "15:26" },
            { "station": "车墩", "arrival": "15:33", "departure": "15:34" },
            { "station": "新桥", "arrival": "15:41", "departure": "15:42" },
            { "station": "春申", "arrival": "15:50", "departure": "15:51" },
            { "station": "莘庄", "arrival": "15:58", "departure": "--" }
          ]
        },
        {
          "train_number": "S1110",
          "type": "大站车",
          "stops": [
            { "station": "金山卫", "arrival": "--", "departure": "15:42" },
            { "station": "亭林", "arrival": "15:54", "departure": "15:55" },
            { "station": "新桥", "arrival": "16:08", "departure": "16:09" },
            { "station": "上海南", "arrival": "16:25", "departure": "--" }
          ]
        },
        {
          "train_number": "S1624",
          "type": "站站停",
          "stops": [
            { "station": "金山卫", "arrival": "--", "departure": "15:50" },
            { "station": "金山园区", "arrival": "15:59", "departure": "16:00" },
            { "station": "亭林", "arrival": "16:06", "departure": "16:07" },
            { "station": "叶榭", "arrival": "16:13", "departure": "16:14" },
            { "station": "车墩", "arrival": "16:21", "departure": "16:22" },
            { "station": "新桥", "arrival": "16:29", "departure": "16:30" },
            { "station": "春申", "arrival": "16:38", "departure": "16:39" },
            { "station": "莘庄", "arrival": "16:46", "departure": "--" }
          ]
        },
        {
          "train_number": "S1006",
          "type": "直达车",
          "stops": [
            { "station": "金山卫", "arrival": "--", "departure": "16:40" },
            { "station": "上海南", "arrival": "17:14", "departure": "--" }
          ]
        },
        {
          "train_number": "S1626",
          "type": "站站停",
          "stops": [
            { "station": "金山卫", "arrival": "--", "departure": "17:00" },
            { "station": "金山园区", "arrival": "17:09", "departure": "17:10" },
            { "station": "亭林", "arrival": "17:16", "departure": "17:17" },
            { "station": "叶榭", "arrival": "17:23", "departure": "17:24" },
            { "station": "车墩", "arrival": "17:31", "departure": "17:32" },
            { "station": "新桥", "arrival": "17:39", "departure": "17:40" },
            { "station": "春申", "arrival": "17:48", "departure": "17:49" },
            { "station": "莘庄", "arrival": "17:56", "departure": "--" }
          ]
        },
        {
          "train_number": "S1204",
          "type": "站站停",
          "stops": [
            { "station": "金山卫", "arrival": "--", "departure": "17:22" },
            { "station": "金山园区", "arrival": "17:31", "departure": "17:32" },
            { "station": "亭林", "arrival": "17:38", "departure": "17:39" },
            { "station": "叶榭", "arrival": "17:45", "departure": "17:46" },
            { "station": "车墩", "arrival": "17:53", "departure": "17:54" },
            { "station": "新桥", "arrival": "18:01", "departure": "18:02" },
            { "station": "春申", "arrival": "18:10", "departure": "18:11" },
            { "station": "莘庄", "arrival": "18:18", "departure": "18:19" },
            { "station": "上海南", "arrival": "18:26", "departure": "--" }
          ]
        },
        {
          "train_number": "S1628",
          "type": "站站停",
          "stops": [
            { "station": "金山卫", "arrival": "--", "departure": "17:50" },
            { "station": "金山园区", "arrival": "17:59", "departure": "18:00" },
            { "station": "亭林", "arrival": "18:06", "departure": "18:07" },
            { "station": "叶榭", "arrival": "18:13", "departure": "18:14" },
            { "station": "车墩", "arrival": "18:21", "departure": "18:22" },
            { "station": "新桥", "arrival": "18:29", "departure": "18:30" },
            { "station": "春申", "arrival": "18:45", "departure": "18:46" },
            { "station": "莘庄", "arrival": "18:53", "departure": "--" }
          ]
        },
        {
          "train_number": "S1008",
          "type": "直达车",
          "stops": [
            { "station": "金山卫", "arrival": "--", "departure": "18:13" },
            { "station": "上海南", "arrival": "18:47", "departure": "--" }
          ]
        },
        {
          "train_number": "S1010",
          "type": "直达车",
          "stops": [
            { "station": "金山卫", "arrival": "--", "departure": "18:38" },
            { "station": "上海南", "arrival": "19:13", "departure": "--" }
          ]
        },
        {
          "train_number": "S1630",
          "type": "站站停",
          "stops": [
            { "station": "金山卫", "arrival": "--", "departure": "18:43" },
            { "station": "金山园区", "arrival": "18:52", "departure": "18:53" },
            { "station": "亭林", "arrival": "18:59", "departure": "19:00" },
            { "station": "叶榭", "arrival": "19:06", "departure": "19:07" },
            { "station": "车墩", "arrival": "19:14", "departure": "19:15" },
            { "station": "新桥", "arrival": "19:22", "departure": "19:23" },
            { "station": "春申", "arrival": "19:31", "departure": "19:32" },
            { "station": "莘庄", "arrival": "19:39", "departure": "--" }
          ]
        },
        {
          "train_number": "S1012",
          "type": "直达车",
          "stops": [
            { "station": "金山卫", "arrival": "--", "departure": "19:28" },
            { "station": "上海南", "arrival": "20:02", "departure": "--" }
          ]
        },
        {
          "train_number": "S1208",
          "type": "站站停",
          "stops": [
            { "station": "金山卫", "arrival": "--", "departure": "19:45" },
            { "station": "金山园区", "arrival": "19:54", "departure": "19:55" },
            { "station": "亭林", "arrival": "20:01", "departure": "20:02" },
            { "station": "叶榭", "arrival": "20:08", "departure": "20:09" },
            { "station": "车墩", "arrival": "20:16", "departure": "20:17" },
            { "station": "新桥", "arrival": "20:24", "departure": "20:25" },
            { "station": "春申", "arrival": "20:33", "departure": "20:34" },
            { "station": "莘庄", "arrival": "20:39", "departure": "20:40" },
            { "station": "上海南", "arrival": "20:47", "departure": "--" }
          ]
        },
        {
          "train_number": "S1206",
          "type": "站站停",
          "stops": [
            { "station": "金山卫", "arrival": "--", "departure": "20:10" },
            { "station": "金山园区", "arrival": "20:19", "departure": "20:20" },
            { "station": "亭林", "arrival": "20:26", "departure": "20:27" },
            { "station": "叶榭", "arrival": "20:33", "departure": "20:34" },
            { "station": "车墩", "arrival": "20:41", "departure": "20:42" },
            { "station": "新桥", "arrival": "20:49", "departure": "20:50" },
            { "station": "春申", "arrival": "20:58", "departure": "20:59" },
            { "station": "莘庄", "arrival": "21:06", "departure": "21:07" },
            { "station": "上海南", "arrival": "21:14", "departure": "--" }
          ]
        },
        {
          "train_number": "S1634",
          "type": "站站停",
          "stops": [
            { "station": "金山卫", "arrival": "--", "departure": "20:31" },
            { "station": "金山园区", "arrival": "20:40", "departure": "20:41" },
            { "station": "亭林", "arrival": "20:47", "departure": "20:48" },
            { "station": "叶榭", "arrival": "20:54", "departure": "20:55" },
            { "station": "车墩", "arrival": "21:02", "departure": "21:03" },
            { "station": "新桥", "arrival": "21:10", "departure": "21:11" },
            { "station": "春申", "arrival": "21:19", "departure": "21:20" },
            { "station": "莘庄", "arrival": "21:27", "departure": "--" }
          ]
        },
        {
          "train_number": "S1160",
          "type": "大站车",
          "stops": [
            { "station": "金山卫", "arrival": "--", "departure": "20:57" },
            { "station": "亭林", "arrival": "21:09", "departure": "21:10" },
            { "station": "新桥", "arrival": "21:19", "departure": "21:20" },
            { "station": "上海南", "arrival": "21:40", "departure": "--" }
          ]
        },
        {
          "train_number": "S1210",
          "type": "站站停",
          "stops": [
            { "station": "金山卫", "arrival": "--", "departure": "21:20" },
            { "station": "金山园区", "arrival": "21:29", "departure": "21:30" },
            { "station": "亭林", "arrival": "21:36", "departure": "21:37" },
            { "station": "叶榭", "arrival": "21:43", "departure": "21:44" },
            { "station": "车墩", "arrival": "21:51", "departure": "21:52" },
            { "station": "新桥", "arrival": "21:59", "departure": "22:00" },
            { "station": "春申", "arrival": "22:08", "departure": "22:09" },
            { "station": "莘庄", "arrival": "22:14", "departure": "22:15" },
            { "station": "上海南", "arrival": "22:22", "departure": "--" }
          ]
        },
        {
          "train_number": "S1014",
          "type": "直达车",
          "stops": [
            { "station": "金山卫", "arrival": "--", "departure": "22:27" },
            { "station": "上海南", "arrival": "23:01", "departure": "--" }
          ]
        }
      ]
    }

}